edwh_sshfs_plugin/__about__.py
edwh_sshfs_plugin/__init__.py
edwh_sshfs_plugin/fabfile.py
edwh_sshfs_plugin-0.2.2.dist-info/METADATA
edwh_sshfs_plugin-0.2.2.dist-info/WHEEL
edwh_sshfs_plugin-0.2.2.dist-info/entry_points.txt
edwh_sshfs_plugin-0.2.2.dist-info/RECORD
