Metadata-Version: 2.3
Name: edwh-sshfs-plugin
Version: 0.2.2
Summary: sshfs project with a plugin to be discovered from the edwh package
Project-URL: Documentation, https://github.com/educationwarehouse/edwh-sshfs-plugin#readme
Project-URL: Issues, https://github.com/educationwarehouse/edwh-sshfs-plugin/issues
Project-URL: Source, https://github.com/educationwarehouse/edwh-sshfs-plugin
Author-email: Remco Boerma <remco.b@educationwarehouse.nl>, Robin van der Noord <robin.vdn@educationwarehouse.nl>
Classifier: Development Status :: 4 - Beta
Classifier: Programming Language :: Python
Classifier: Programming Language :: Python :: 3.10
Classifier: Programming Language :: Python :: 3.11
Classifier: Programming Language :: Python :: 3.12
Classifier: Programming Language :: Python :: Implementation :: CPython
Classifier: Programming Language :: Python :: Implementation :: PyPy
Requires-Python: >=3.10
Requires-Dist: edwh
Requires-Dist: plumbum>=1.8.1
Provides-Extra: async
Requires-Dist: anyio; extra == 'async'
Requires-Dist: trio; extra == 'async'
Provides-Extra: dev
Requires-Dist: black; extra == 'dev'
Requires-Dist: hatch; extra == 'dev'
Requires-Dist: pytest; extra == 'dev'
Requires-Dist: pytest-anyio; extra == 'dev'
Requires-Dist: python-semantic-release<8; extra == 'dev'
